Disys_DL.py
Disys_calib.py
PyDisys-1.1.4.dist-info/METADATA
PyDisys-1.1.4.dist-info/WHEEL
PyDisys-1.1.4.dist-info/top_level.txt
PyDisys-1.1.4.dist-info/RECORD
