Metadata-Version: 2.1
Name: PyDisys
Version: 1.1.4
Summary: Disys library for calibration
Author: NF
License: UNKNOWN
Platform: UNKNOWN
Requires-Dist: matplotlib (>=3.5.1)
Requires-Dist: mvtec-halcon (>=21050.0.0)
Requires-Dist: numpy (>=1.21.2)
Requires-Dist: pandas (>=1.3.4)
Requires-Dist: Pillow (>=9.1.0)
Requires-Dist: pyrenn (>=0.1)
Requires-Dist: scikit-learn (>=1.0.2)
Requires-Dist: split-folders (>=0.5.1)
